Metadata-Version: 2.1
Name: mac-alerts
Version: 1.0.3
Summary: Play MacOS Notification Sounds - The Easy Way.
Home-page: https://github.com/chrischma/mac_alerts
Author: Christoph Schmalfuss
Author-email: post@christoph-schmalfuss.de
License: CC-BY-4.0
Platform: UNKNOWN
Classifier: Operating System :: MacOS
Classifier: Programming Language :: Python :: 3
Classifier: Programming Language :: Python :: 3.4
Classifier: Programming Language :: Python :: 3.5
